pha/__about__.py
pha/__init__.py
pha-0.0.0.dist-info/METADATA
pha-0.0.0.dist-info/WHEEL
pha-0.0.0.dist-info/RECORD
