Metadata-Version: 2.4
Name: pha
Version: 0.0.0
Summary: WIP: Dynamical systems
Project-URL: Documentation, https://github.com/harnesslabs/pha
Author: HarnessLabs
Requires-Python: >=3.10
